tasklin/__init__.py
tasklin/cli.py
tasklin/factory.py
tasklin/models.py
tasklin/providers/__init__.py
tasklin/providers/base.py
tasklin/providers/claude_provider.py
tasklin/providers/deepseek_provider.py
tasklin/providers/ollama_provider.py
tasklin/providers/openai_provider.py
tasklin-0.0.3.dist-info/licenses/LICENSE
tasklin-0.0.3.dist-info/METADATA
tasklin-0.0.3.dist-info/WHEEL
tasklin-0.0.3.dist-info/entry_points.txt
tasklin-0.0.3.dist-info/top_level.txt
tasklin-0.0.3.dist-info/RECORD
