Metadata-Version: 2.4
Name: tasklin
Version: 0.0.3
Summary: A single CLI to connect with OpenAI, Ollama, and more AI providers.
Author-email: jetroni <jetronsaiti@gmail.com>, FehmiHavziu <femi.havziu123@gmail.com>
License: MIT License
Requires-Python: >=3.8
License-File: LICENSE
Requires-Dist: typer>=0.9
Requires-Dist: click>=8.1
Requires-Dist: rich>=13.0
Requires-Dist: openai>=1.0.0
Requires-Dist: anthropic>=0.64.0
Requires-Dist: pydantic>=1.10.22
Dynamic: license-file
